ynab_cli/__init__.py
ynab_cli/py.typed
ynab_cli/adapters/__init__.py
ynab_cli/adapters/rich/__init__.py
ynab_cli/adapters/rich/io.py
ynab_cli/adapters/textual/__init__.py
ynab_cli/adapters/textual/io.py
ynab_cli/adapters/ynab/__init__.py
ynab_cli/adapters/ynab/client.py
ynab_cli/adapters/ynab/errors.py
ynab_cli/adapters/ynab/types.py
ynab_cli/adapters/ynab/util.py
ynab_cli/adapters/ynab/api/__init__.py
ynab_cli/adapters/ynab/api/accounts/__init__.py
ynab_cli/adapters/ynab/api/accounts/create_account.py
ynab_cli/adapters/ynab/api/accounts/get_account_by_id.py
ynab_cli/adapters/ynab/api/accounts/get_accounts.py
ynab_cli/adapters/ynab/api/budgets/__init__.py
ynab_cli/adapters/ynab/api/budgets/get_budget_by_id.py
ynab_cli/adapters/ynab/api/budgets/get_budget_settings_by_id.py
ynab_cli/adapters/ynab/api/budgets/get_budgets.py
ynab_cli/adapters/ynab/api/categories/__init__.py
ynab_cli/adapters/ynab/api/categories/get_categories.py
ynab_cli/adapters/ynab/api/categories/get_category_by_id.py
ynab_cli/adapters/ynab/api/categories/get_month_category_by_id.py
ynab_cli/adapters/ynab/api/categories/update_category.py
ynab_cli/adapters/ynab/api/categories/update_month_category.py
ynab_cli/adapters/ynab/api/months/__init__.py
ynab_cli/adapters/ynab/api/months/get_budget_month.py
ynab_cli/adapters/ynab/api/months/get_budget_months.py
ynab_cli/adapters/ynab/api/payee_locations/__init__.py
ynab_cli/adapters/ynab/api/payee_locations/get_payee_location_by_id.py
ynab_cli/adapters/ynab/api/payee_locations/get_payee_locations.py
ynab_cli/adapters/ynab/api/payee_locations/get_payee_locations_by_payee.py
ynab_cli/adapters/ynab/api/payees/__init__.py
ynab_cli/adapters/ynab/api/payees/get_payee_by_id.py
ynab_cli/adapters/ynab/api/payees/get_payees.py
ynab_cli/adapters/ynab/api/payees/update_payee.py
ynab_cli/adapters/ynab/api/scheduled_transactions/__init__.py
ynab_cli/adapters/ynab/api/scheduled_transactions/create_scheduled_transaction.py
ynab_cli-0.7.1.dist-info/METADATA
ynab_cli-0.7.1.dist-info/WHEEL
ynab_cli-0.7.1.dist-info/entry_points.txt
ynab_cli-0.7.1.dist-info/licenses/LICENSE.md
ynab_cli-0.7.1.dist-info/RECORD
