Metadata-Version: 2.4
Name: ynab-cli
Version: 0.7.1
Summary: YNAB Command Line Interface
Project-URL: Changelog, https://github.com/jeffsawatzky/ynab-cli/blob/main/CHANGELOG.md
Project-URL: Documentation, https://jeffsawatzky.github.io/ynab-cli/
Project-URL: Funding, https://github.com/sponsors/jeffsawatzky
Project-URL: Releases, https://github.com/jeffsawatzky/ynab-cli/releases
Project-URL: Source, https://github.com/jeffsawatzky/ynab-cli
Author: Jeff Sawatzky
License-Expression: MIT
License-File: LICENSE.md
Keywords: budget,cli,click,textual,ynab
Classifier: Development Status :: 4 - Beta
Classifier: Intended Audience :: End Users/Desktop
Classifier: Programming Language :: Python :: 3.11
Classifier: Programming Language :: Python :: 3.12
Classifier: Programming Language :: Python :: 3.13
Classifier: Topic :: Office/Business :: Financial
Classifier: Topic :: Utilities
Requires-Python: <4.0.0,>=3.11
Requires-Dist: anyio~=4.11
Requires-Dist: attrs~=25.3
Requires-Dist: click-default-group~=1.2
Requires-Dist: click~=8.3
Requires-Dist: httpx~=0.28
Requires-Dist: lagom~=2.7
Requires-Dist: python-dateutil~=2.9
Requires-Dist: python-dotenv~=1.1
Requires-Dist: rapidfuzz~=3.14
Requires-Dist: rich~=14.1
Requires-Dist: rule-engine~=4.5
Requires-Dist: textual-fspicker~=0.6
Requires-Dist: textual~=6.3
Requires-Dist: typing-extensions~=4.15
Requires-Dist: uvloop~=0.21
